polywrap_manifest/__init__.py
polywrap_manifest/deserialize.py
polywrap_manifest/errors.py
polywrap_manifest/manifest.py
polywrap_manifest/py.typed
polywrap_manifest/wrap_0_1.py
polywrap_manifest-0.1.2.dist-info/METADATA
polywrap_manifest-0.1.2.dist-info/WHEEL
polywrap_manifest-0.1.2.dist-info/RECORD
