Metadata-Version: 2.1
Name: polywrap-manifest
Version: 0.1.2
Summary: WRAP manifest
Author: Niraj
Author-email: niraj@polywrap.io
Requires-Python: >=3.10,<4.0
Classifier: Programming Language :: Python :: 3
Classifier: Programming Language :: Python :: 3.10
Classifier: Programming Language :: Python :: 3.11
Requires-Dist: polywrap-msgpack (==0.1.2)
Requires-Dist: pydantic (>=1.10.2,<2.0.0)
